shortipy/__init__.py
shortipy/controllers/__init__.py
shortipy/controllers/api/__init__.py
shortipy/controllers/api/auth.py
shortipy/controllers/api/url.py
shortipy/controllers/resolution.py
shortipy/services/__init__.py
shortipy/services/auth.py
shortipy/services/config.py
shortipy/services/exceptions.py
shortipy/services/hash.py
shortipy/services/redis.py
shortipy/services/serialization.py
shortipy/services/url.py
shortipy-1.3.2.dist-info/LICENSE
shortipy-1.3.2.dist-info/WHEEL
shortipy-1.3.2.dist-info/METADATA
shortipy-1.3.2.dist-info/RECORD
