Metadata-Version: 2.1
Name: shortipy
Version: 1.3.2
Summary: Shortipy is a RESTful Web API, written in Python language and based on the Flask micro-framework, designed to manage shortened links.
Home-page: https://github.com/CoffeePerry/shortipy
License: GPL-3.0
Keywords: shortipy,url,shortener
Author: Simone Perini
Author-email: perinisimone98@gmail.com
Requires-Python: >=3.10,<4.0
Classifier: Development Status :: 5 - Production/Stable
Classifier: Framework :: Flask
Classifier: Intended Audience :: Developers
Classifier: License :: OSI Approved :: GNU General Public License v3 (GPLv3)
Classifier: Natural Language :: English
Classifier: Operating System :: OS Independent
Classifier: Programming Language :: Python :: 3
Classifier: Programming Language :: Python :: 3.10
Classifier: Programming Language :: Python :: 3.11
Classifier: Topic :: Communications
Classifier: Topic :: Utilities
Classifier: Typing :: Typed
Requires-Dist: flask (>=2.2.2,<3.0.0)
Requires-Dist: flask-bcrypt (>=1.0.1,<2.0.0)
Requires-Dist: flask-jwt-extended (>=4.4.4,<5.0.0)
Requires-Dist: flask-marshmallow (>=0.14.0,<0.15.0)
Requires-Dist: flask-redis (>=0.4.0,<0.5.0)
Requires-Dist: webargs (>=8.2.0,<9.0.0)
Project-URL: Repository, https://github.com/CoffeePerry/shortipy
